src/__init__.py
src/analyze.py
src/base.py
src/encodings.py
src/generate_example.py
src/losses.py
src/segmentation_analysis.py
tests/__init__.py
tests/test_analyze.py
tests/test_base.py
tests/test_encodings.py
tests/test_generate_example.py
tests/test_losses.py
tests/test_segmentation_analysis.py
predictions_analyzer_tpmeli-0.0.21.dist-info/LICENSE
predictions_analyzer_tpmeli-0.0.21.dist-info/METADATA
predictions_analyzer_tpmeli-0.0.21.dist-info/WHEEL
predictions_analyzer_tpmeli-0.0.21.dist-info/top_level.txt
predictions_analyzer_tpmeli-0.0.21.dist-info/RECORD
